libqutrub/__init__.py
libqutrub/alefmaddaverbtable.py
libqutrub/ar_ctype.py
libqutrub/ar_verb.py
libqutrub/arabic_const.py
libqutrub/classnoun.py
libqutrub/classverb.py
libqutrub/conjugate.py
libqutrub/conjugatedisplay.py
libqutrub/conjugator.py
libqutrub/mosaref_main.py
libqutrub/stack.py
libqutrub/triverbtable.py
libqutrub/verb_const.py
libqutrub/verb_db.py
libqutrub/verb_valid.py
libqutrub-1.2.4.1.dist-info/DESCRIPTION.rst
libqutrub-1.2.4.1.dist-info/METADATA
libqutrub-1.2.4.1.dist-info/RECORD
libqutrub-1.2.4.1.dist-info/WHEEL
libqutrub-1.2.4.1.dist-info/metadata.json
libqutrub-1.2.4.1.dist-info/top_level.txt
