Metadata-Version: 1.1
Name: libqutrub
Version: 1.2.4.1
Summary: libqutrub Arabic verb conjuagtion library
Home-page: http://libqutrub.sourceforge.net/
Author: Taha Zerrouki
Author-email: taha.zerrouki@gmail.com
License: GPL
Platform: UNKNOWN
Classifier: Development Status :: 5 - Production/Stable
Classifier: Intended Audience :: End Users/Desktop
Classifier: Programming Language :: Python
